pyH2A/Discounted_Cash_Flow.py
pyH2A/__init__.py
pyH2A/__main__.py
pyH2A/cli_pyH2A.py
pyH2A/run_pyH2A.py
pyH2A/Analysis/Comparative_MC_Analysis.py
pyH2A/Analysis/Cost_Contributions_Analysis.py
pyH2A/Analysis/Development_Distance_Time_Analysis.py
pyH2A/Analysis/Monte_Carlo_Analysis.py
pyH2A/Analysis/Sensitivity_Analysis.py
pyH2A/Analysis/Waterfall_Analysis.py
pyH2A/Analysis/__init__.py
pyH2A/Config/Defaults.md
pyH2A/Config/__init__.py
pyH2A/Example/210511_Future_PEC_Type_4.md
pyH2A/Example/210613_PV_E.md
pyH2A/Example/211109_Future_PEC_Type_1_Figure_Test.md
pyH2A/Example/Future_PEC_Type_1_Monte_Carlo.csv
pyH2A/Example/Future_PEC_Type_4_Monte_Carlo.csv
pyH2A/Example/PV_E_Monte_Carlo.csv
pyH2A/Example/__init__.py
pyH2A/Lookup_Tables/GDP_Implicit_Deflator_Price_Index.csv
pyH2A/Lookup_Tables/Labor_Index.csv
pyH2A/Lookup_Tables/MACRS.csv
pyH2A/Lookup_Tables/Plant_Cost_Index.csv
pyH2A/Lookup_Tables/SRI_Chemical_Price_Index.csv
pyH2A/Lookup_Tables/__init__.py
pyH2A/Lookup_Tables/Hourly_Irradiation_Data/__init__.py
pyH2A/Lookup_Tables/Hourly_Irradiation_Data/tmy_34.859_-116.889_2006_2015.csv
pyH2A/Lookup_Tables/Utility_Cost/Commercial_Electricity_AEO_2017_Reference_Case.csv
pyH2A/Lookup_Tables/Utility_Cost/Commercial_Natural_Gas_AEO_2017_Reference_Case.csv
pyH2A/Lookup_Tables/Utility_Cost/Industrial_Electricity_AEO_2017_Reference_Case.csv
pyH2A/Lookup_Tables/Utility_Cost/Industrial_Natural_Gas_AEO_2017_Reference_Case.csv
pyH2A/Lookup_Tables/Utility_Cost/Woody_Biomass_AEO_2017_Reference_Case.csv
pyH2A/Lookup_Tables/Utility_Cost/__init__.py
pyH2A/Other/PCE_Clipart.svg
pyH2A/Other/PEC_Clipart.png
pyH2A/Other/PV_E_Clipart.png
pyH2A/Other/PV_E_Clipart.svg
pyH2A/Other/Photocatalytic_Clipart.png
pyH2A/Other/Photocatalytic_Clipart.svg
pyH2A/Other/Sun.svg
pyH2A/Other/__init__.py
pyH2A/Other/pyH2A.png
pyH2A/Other/pyH2A.svg
pyH2A/Other/pyH2A_source.svg
pyH2A/Plugins/Capital_Cost_Plugin.py
pyH2A/Plugins/Catalyst_Separation_Plugin.py
pyH2A/Plugins/Fixed_Operating_Cost_Plugin.py
pyH2A-0.0a8.dist-info/LICENSE
pyH2A-0.0a8.dist-info/LICENSE-CC-BY.txt
pyH2A-0.0a8.dist-info/METADATA
pyH2A-0.0a8.dist-info/WHEEL
pyH2A-0.0a8.dist-info/entry_points.txt
pyH2A-0.0a8.dist-info/top_level.txt
pyH2A-0.0a8.dist-info/RECORD
