Metadata-Version: 2.1
Name: pyH2A
Version: 0.0a8
Summary: A framework for the analysis of hydrogen production cost
Home-page: https://github.com/jschneidewind/pyH2A
Author: Jacob Schneidewind
Author-email: pyH2A.pypi@gmail.com
License: UNKNOWN
Project-URL: Bug Tracker, https://github.com/jschneidewind/pyH2A/issues
Platform: UNKNOWN
Classifier: Programming Language :: Python :: 3
Classifier: License :: OSI Approved :: MIT License
Classifier: Operating System :: OS Independent
Requires-Python: >=3.7
License-File: LICENSE
License-File: LICENSE-CC-BY.txt
Requires-Dist: click
Requires-Dist: numpy
Requires-Dist: scipy
Requires-Dist: pandas
Requires-Dist: matplotlib
